{
  "id": "project-home",
  "name": "Project",
  "path": "/project-home",
  "icon": "FaFolderOpen",
  "gadgets": [
    {
      "name": "tileGadget1",
      "gadgetType": "tile",
      "showHeader":false,
      "showFooter" :false,
      "colSpan":"col-span-2",
      "colorRotation":true,
      "gadgetOptions": {
        "title": "Overall Project Completion",
        "value": "85",
        "uom":"%",
        "icon": "FaCheckCircle",
        "link": "/project-completion"
      }
    },
    {
      "name": "tileGadget2",
      "gadgetType": "tile",
      "showHeader":false,
      "showFooter" :false,
      "colSpan":"col-span-2",
      "colorRotation":true,
      "gadgetOptions": {
        "title": "Total Wells Analyzed",
        "value": "12",
        "uom":"Wells",
        "icon": "FaOilCan",
        "link": "/wells-overview"
      }
    },
    {
      "name": "tileGadget3",
      "gadgetType": "tile",
      "showHeader":false,
      "showFooter" :false,
      "colSpan":"col-span-2",
      "colorRotation":true,
      "gadgetOptions": {
        "title": "Production Forecast (Total)",
        "value": "6.5",
        "uom":"MMbbl",
        "icon": "FaChartLine",
        "link": "/production-forecast"
      }
    },
    {
      "name": "tileGadget4",
      "gadgetType": "tile",
      "showHeader":false,
      "showFooter" :false,
      "colSpan":"col-span-2",
      "colorRotation":true,
      "gadgetOptions": {
        "title": "Water Cut (Average)",
        "value": "32",
        "uom":"%",
        "icon": "FaTint",
        "link": "/water-cut"
      }
    },
    {
      "name": "tileGadget5",
      "gadgetType": "tile",
      "showHeader":false,
      "showFooter" :false,
      "colSpan":"col-span-2",
      "colorRotation":true,
      "gadgetOptions": {
        "title": "Reservoir Simulation Runs",
        "value": "8",
        "uom":"Simulations",
        "icon": "FaCogs",
        "link": "/reservoir-simulation"
      }
    },
    {
      "name": "tileGadget6",
      "gadgetType": "tile",
      "showHeader":false,
      "showFooter" :false,
      "colSpan":"col-span-2",
      "colorRotation":true,
      "gadgetOptions": {
        "title": "Total Gas Production",
        "value": "18",
        "uom":"MMscf/day",
        "icon": "FaGasPump",
        "link": "/gas-production"
      }
    },
    {
      "name": "mapGadget",
      "gadgetType": "map",
      "title": "Wells",
      "showHeader": true,
      "showFooter": true,
      "icon": "FaMap",
      "colSpan": "col-span-4",  
      "gadgetOptions": {
       "datasource": "/data/mock-data/well-map.json",
       "height":"300px"
    }
  }
  ]
}
